kegg_a_nog/__init__.py
kegg_a_nog/data_processing.py
kegg_a_nog/data_processing_multi.py
kegg_a_nog/grouped_heatmap.py
kegg_a_nog/grouped_heatmap_multi.py
kegg_a_nog/kegg_a_nog.py
kegg_a_nog/kegg_a_nog_multi.py
kegg_a_nog/simple_heatmap.py
kegg_a_nog/simple_heatmap_multi.py
kegganog/KO_decode.py
kegganog/__init__.py
kegganog/barplot.py
kegganog/boxplot.py
kegganog/corrnet.py
kegganog/data_processing.py
kegganog/data_processing_multi.py
kegganog/grouped_heatmap.py
kegganog/grouped_heatmap_multi.py
kegganog/heatmap.py
kegganog/kegganog.py
kegganog/kegganog_multi.py
kegganog/radarplot.py
kegganog/simple_heatmap.py
kegganog/simple_heatmap_multi.py
kegganog/version.py
kegganog/cheatmaps/__init__.py
kegganog/cheatmaps/grouped_heatmap.py
kegganog/cheatmaps/grouped_heatmap_multi.py
kegganog/cheatmaps/simple_heatmap.py
kegganog/cheatmaps/simple_heatmap_multi.py
kegganog/kgnplot/__init__.py
kegganog/kgnplot/barplot.py
kegganog/kgnplot/base.py
kegganog/kgnplot/boxplot.py
kegganog/kgnplot/corrnet.py
kegganog/kgnplot/heatmap.py
kegganog/kgnplot/radarplot.py
kegganog/kgnplot/stackedbar.py
kegganog/kgnplot/streamgraph.py
kegganog/processing/KEGG_decoder.py
kegganog/processing/KO_decode.py
kegganog/processing/__init__.py
kegganog/processing/data_processing.py
kegganog/processing/data_processing_multi.py
src/KEGG_decoder.py
src/KO_decode.py
src/__init__.py
src/boxplot.py
src/data_processing.py
src/data_processing_multi.py
src/grouped_heatmap.py
src/grouped_heatmap_multi.py
src/kegganog.py
src/kegganog_multi.py
src/simple_heatmap.py
src/simple_heatmap_multi.py
src/version.py
kegganog-1.1.19.dist-info/LICENSE
kegganog-1.1.19.dist-info/METADATA
kegganog-1.1.19.dist-info/WHEEL
kegganog-1.1.19.dist-info/entry_points.txt
kegganog-1.1.19.dist-info/top_level.txt
kegganog-1.1.19.dist-info/RECORD
