Metadata-Version: 2.2
Name: kegganog
Version: 1.1.19
Summary: A tool for generating KEGG heatmaps from eggNOG-mapper outputs.
Home-page: https://github.com/iliapopov17/KEGGaNOG
Author: Ilia Popov
Author-email: iljapopov17@gmail.com
Requires-Python: >=3.6
License-File: LICENSE
Requires-Dist: matplotlib==3.10.0
Requires-Dist: numpy==2.2.0
Requires-Dist: pandas==2.2.3
Requires-Dist: plotly==5.24.1
Requires-Dist: pyparsing==3.2.0
Requires-Dist: scipy==1.14.1
Requires-Dist: seaborn==0.13.2
Requires-Dist: tanglegram==0.2.0
Requires-Dist: tqdm==4.67.1
Requires-Dist: networkx==3.4.2
Dynamic: author
Dynamic: author-email
Dynamic: description
Dynamic: description-content-type
Dynamic: home-page
Dynamic: requires-dist
Dynamic: requires-python
Dynamic: summary
